momonga/__init__.py
momonga/momonga.py
momonga/momonga_device_enum.py
momonga/momonga_exception.py
momonga/momonga_response.py
momonga/momonga_session_manager.py
momonga/momonga_sk_wrapper.py
momonga-0.3.0.dist-info/licenses/LICENSE
momonga-0.3.0.dist-info/METADATA
momonga-0.3.0.dist-info/WHEEL
momonga-0.3.0.dist-info/top_level.txt
momonga-0.3.0.dist-info/RECORD
