Metadata-Version: 2.4
Name: momonga
Version: 0.3.0
Summary: Python Route B Library: A Communicator for Low-voltage Smart Electric Energy Meters
Home-page: https://github.com/nbtk/momonga
Author: nbtk
License: MIT
Classifier: Development Status :: 4 - Beta
Classifier: Programming Language :: Python :: 3
Classifier: License :: OSI Approved :: MIT License
Requires-Python: >=3.11
License-File: LICENSE
Requires-Dist: pyserial~=3.5
Dynamic: author
Dynamic: classifier
Dynamic: description
Dynamic: description-content-type
Dynamic: home-page
Dynamic: license
Dynamic: license-file
Dynamic: requires-dist
Dynamic: requires-python
Dynamic: summary
